{"components":[{"figmaName":"Icon/Outline/plus","codeComponent":"Icon","type":"INSTANCE","nodeId":"11:215","componentId":"11:6"},{"figmaName":"Social-icon-linkedin","codeComponent":"Social-icon-linkedin","type":"INSTANCE","nodeId":"11:308","componentId":"11:8"},{"figmaName":"Social-icon-instagram","codeComponent":"Social-icon-instagram","type":"INSTANCE","nodeId":"11:309","componentId":"11:11"},{"figmaName":"Social-icon-facebook","codeComponent":"Social-icon-facebook","type":"INSTANCE","nodeId":"11:310","componentId":"11:16"}],"tokens":{"colors":{"2021":"#333333","Mask group":"#c7c4c0","*":"#cf7745","I'm Jason Pereira":"#6a92c1","Helping companies and people to turn their ideas into design.":"#4b4b4b","Frame 430":"#000000","Call to action":"#ffffff","-Or Call to action":"#000000","Frame 64":"#ffffff","Frame":"#ffffff","Vector":"#000000","Frame 445":"#cfcfcf","Frame 438":"#ffffff","About":"#706352","Digital Designer based in São Paulo, in love to undertake.":"#333333","Helping companies and people to turn their ideas into design. A very good design and customer experience.":"#4b4b4b","Frame 436":"#434343","Selected Clients":"#434343","Icon":"#434343","Frame 447":"#cfcfcf","Frame 444":"#333333","Project(s)":"#333333","Arrow 3":"#ffffff","Rectangle 65":"#d9d9d9","Frame 421":"#333333","Ellipse 23":"#333333","Sesc Brasil":"#333333","Website Institucional":"#333333","Frame 472":"#000000","See more":"#333333","W/Express":"#333333","EBANX":"#333333","Frame 446":"#2d2d2d","CVV":"#333333","Frame 448":"#000000","Nome do projeto":"#333333","+10 Years of experience":"#ffffff","UI / UX Design":"#ffffff","Efficient and unique interfaces tailored to your project needs.":"#ffffff","Art Direction":"#ffffff","Behavior-based analysis of users in your project.":"#ffffff","Photography":"#ffffff","Art direction to enhance visual communication.":"#ffffff","Objective process":"#ffffff","Frame 353":"#ffffff","Define":"#ffffff","Frame 354":"#ffffff","Discover":"#ffffff","Frame 355":"#ffffff","Create":"#ffffff","Frame 356":"#ffffff","Deliver":"#ffffff","Arrow 7":"#ffffff","Arrow 8":"#ffffff","Arrow 9":"#ffffff","Frame 443":"#f4f4f4","Testimonials":"#706352","Frame 347":"#000000","” Lorem ipsum dolor sit amet, consectetur adipiscing elit, sed do eiusmod tempor. “":"#333333","Website":"#333333","Frame 449":"#000000","Frame 450":"#000000","Rectangle 66":"#101010","Rectangle 67":"#d9d9d9","Rectangle 68":"#d9d9d9","Rectangle 69":"#d9d9d9","Frame 58":"#2d2c2c","Line 1":"#000000","JASON PEREIRA":"#000000","Lorem ipsum dolor sit amet, consectetur adipiscing elit, sed do eiusmod tempor incididunt ut labore":"#c7c7c7","MENU":"#ffffff","Início":"#ffffff","Quem somos":"#ffffff","Serviços":"#ffffff","Blog":"#ffffff","Dúvidas Frequentes":"#ffffff","Contato":"#ffffff","©2023 Peres Global Insurance. All right reserved.":"#ffffff","Política de Cookies":"#ffffff","Política de privacidade":"#ffffff","Frame 468":"#ffffff","LET'S GET":"#535353","Frame 467":"#ffffff","Frame 466":"#ffffff","IN TOUCH":"#535353","Frame 10":"#454545","Projects":"#706352","Contact":"#ffffff"},"variables":[],"styles":[]},"thumbnailUrl":"https://figma-alpha-api.s3.us-west-2.amazonaws.com/images/e7697f58-f80a-4826-989b-6b6cd25f026d","referenceCode":null,"mcpRaw":"MCP error -32602: Tool get_design_context not found","meta":{"nodeId":"11:20","fileKey":"yaaBswjQKYKmnRTdPpS9Xl","fetchedAt":"2026-05-31T17:42:34.682Z","componentCount":4,"variableCount":0,"styleCount":0,"mcpAvailable":true}}